Workbook

Sheet HNY_CB1_filter
A1: Project ID | B1: Project Name | C1: Project Start Date | D1: Project Completion Date | E1: Building ID | F1: Number | G1: Street | H1: Borough | I1: Postcode | J1: BBL | K1: BIN | L1: Community Board | M1: Council District | N1: Census Tract | O1: NTA - Neighborhood Tabulation Area | P1: Latitude | Q1: Longitude | R1: Latitude (Internal) | S1: Longitude (Internal) | T1: Building Completion Date | U1: Reporting Construction Type | V1: Extended Affordability Only | W1: Prevailing Wage Status | X1: Extremely Low Income Units | Y1: Very Low Income Units | Z1: Low Income Units | AA1: Moderate Income Units | AB1: Middle Income Units | AC1: Other Income Units | AD1: Studio Units | AE1: 1-BR Units | AF1: 2-BR Units | AG1: 3-BR Units | AH1: 4-BR Units | AI1: 5-BR Units | AJ1: 6-BR+ Units | AK1: Unknown-BR Units | AL1: Counted Rental Units | AM1: Counted Homeownership Units | AN1: All Counted Units | AO1: Total Units
A2: 74488 | B2: MORNINGSIDE HEIGHTS III. HPO.FY25 | C2: 45838 | E2: 37512 | F2: 106 | G2: WEST 105 STREET | H2: Manhattan | I2: 10025 | J2: 1018590037 | K2: 1055923 | L2: MN-07 | M2: 7 | N2: 189 | O2: MN0703 | P2: 40.798689 | Q2: -73.963676 | R2: 40.798613 | S2: -73.964081 | U2: Preservation | V2: Yes | W2: Non Prevailing Wage | X2: 4 | Y2: 1 | Z2: 1 | AA2: 2 | AB2: 3 | AF2: 1 | AG2: 5 | AH2: 3 | AI2: 2 | AL2: 11 | AN2: 11 | AO2: 19
A3: 74488 | B3: MORNINGSIDE HEIGHTS III. HPO.FY25 | C3: 45838 | E3: 37594 | F3: 123 | G3: WEST 106 STREET | H3: Manhattan | I3: 10025 | J3: 1018610121 | K3: 1055982 | L3: MN-07 | M3: 7 | N3: 193 | O3: MN0703 | P3: 40.799634 | Q3: -73.963784 | R3: 40.799905 | S3: -73.963726 | U3: Preservation | V3: Yes | W3: Non Prevailing Wage | Y3: 1 | Z3: 1 | AA3: 3 | AB3: 5 | AF3: 3 | AG3: 4 | AH3: 3 | AL3: 10 | AN3: 10 | AO3: 10
A4: 74488 | B4: MORNINGSIDE HEIGHTS III. HPO.FY25 | C4: 45838 | E4: 37595 | F4: 125 | G4: WEST 106 STREET | H4: Manhattan | I4: 10025 | J4: 1018610021 | K4: 1055959 | L4: MN-07 | M4: 7 | N4: 193 | O4: MN0703 | P4: 40.799661 | Q4: -73.963849 | R4: 40.79993 | S4: -73.963787 | U4: Preservation | V4: Yes | W4: Non Prevailing Wage | Y4: 2 | Z4: 1 | AA4: 2 | AB4: 5 | AF4: 4 | AG4: 4 | AH4: 2 | AL4: 10 | AN4: 10 | AO4: 10
A5: 74488 | B5: MORNINGSIDE HEIGHTS III. HPO.FY25 | C5: 45838 | E5: 37596 | F5: 127 | G5: WEST 106 STREET | H5: Manhattan | I5: 10025 | J5: 1018610020 | K5: 1055958 | L5: MN-07 | M5: 7 | N5: 193 | O5: MN0703 | P5: 40.799688 | Q5: -73.96391 | R5: 40.799957 | S5: -73.963852 | U5: Preservation | V5: Yes | W5: Non Prevailing Wage | Y5: 1 | Z5: 2 | AA5: 1 | AB5: 6 | AF5: 5 | AG5: 2 | AH5: 3 | AL5: 10 | AN5: 10 | AO5: 10
A6: 74488 | B6: MORNINGSIDE HEIGHTS III. HPO.FY25 | C6: 45838 | E6: 37723 | F6: 203 | G6: WEST 108 STREET | H6: Manhattan | I6: 10025 | J6: 1018800027 | K6: 1056680 | L6: MN-07 | M6: 7 | N6: 195 | O6: MN0703 | P6: 40.801904 | Q6: -73.965123 | R6: 40.802165 | S6: -73.965177 | U6: Preservation | V6: Yes | W6: Non Prevailing Wage | X6: 7 | Y6: 2 | Z6: 1 | AA6: 2 | AB6: 6 | AC6: 1 | AD6: 1 | AF6: 3 | AG6: 12 | AH6: 3 | AL6: 19 | AN6: 19 | AO6: 21
A7: 76578 | B7: PUEBLO NUEVO.HUDMF.FY25 | C7: 45838 | D7: 45838 | E7: 805337 | F7: 210 | G7: STANTON STREET | H7: Manhattan | I7: 10002 | J7: 1003450048 | K7: 1004151 | L7: MN-03 | M7: 2 | N7: 2201 | O7: MN0302 | P7: 40.719598 | Q7: -73.982363 | R7: 40.720103 | S7: -73.982175 | T7: 45838 | U7: Preservation | V7: Yes | W7: Non Prevailing Wage | X7: 139 | Y7: 19 | Z7: 12 | AA7: 1 | AC7: 1 | AE7: 78 | AF7: 72 | AG7: 22 | AL7: 172 | AN7: 172 | AO7: 172
A8: 76639 | B8: WEST 104TH STREET.HUDMF.FY25 | C8: 45838 | E8: 25352 | F8: 82 | G8: MANHATTAN AVENUE | H8: Manhattan | I8: 10025 | J8: 1018390045 | K8: 1055483 | L8: MN-07 | M8: 7 | N8: 189 | O8: MN0703 | P8: 40.797056 | Q8: -73.96263 | R8: 40.797119 | S8: -73.962276 | U8: Preservation | V8: No | W8: Non Prevailing Wage | X8: 14 | Y8: 3 | Z8: 2 | AC8: 1 | AD8: 5 | AE8: 10 | AF8: 1 | AG8: 4 | AL8: 20 | AN8: 20 | AO8: 20
A9: 76639 | B9: WEST 104TH STREET.HUDMF.FY25 | C9: 45838 | E9: 37505 | F9: 73 | G9: WEST 104 STREET | H9: Manhattan | I9: 10025 | J9: 1018400005 | K9: 1055488 | L9: MN-07 | M9: 7 | N9: 189 | O9: MN0703 | P9: 40.797773 | Q9: -73.963474 | R9: 40.797841 | S9: -73.96303 | U9: Preservation | V9: No | W9: Non Prevailing Wage | X9: 29 | Y9: 5 | Z9: 5 | AE9: 14 | AF9: 5 | AG9: 15 | AH9: 5 | AL9: 39 | AN9: 39 | AO9: 39
A10: 74451 | B10: 45TH STREET HOUSING PARTNERS LLC.PLP.FY25 | C10: 45835 | E10: 33189 | F10: 357 | G10: WEST 45 STREET | H10: Manhattan | I10: 10036 | J10: 1010360005 | K10: 1085020 | L10: MN-04 | M10: 3 | N10: 12101 | O10: MN0402 | P10: 40.759826 | Q10: -73.989947 | R10: 40.760279 | S10: -73.990463 | U10: Preservation | V10: No | W10: Non Prevailing Wage | X10: 8 | Y10: 10 | Z10: 1 | AA10: 1 | AE10: 10 | AF10: 10 | AL10: 20 | AN10: 20 | AO10: 20
A11: 74451 | B11: 45TH STREET HOUSING PARTNERS LLC.PLP.FY25 | C11: 45835 | E11: 805624 | F11: 351 | G11: WEST 45 STREET | H11: Manhattan | I11: 10036 | J11: 1010360005 | K11: 1025006 | L11: MN-04 | M11: 3 | N11: 12101 | O11: MN0402 | P11: 40.759774 | Q11: -73.989828 | R11: 40.760279 | S11: -73.990463 | U11: Preservation | V11: No | W11: Non Prevailing Wage | X11: 9 | Y11: 9 | Z11: 1 | AA11: 1 | AE11: 10 | AF11: 10 | AL11: 20 | AN11: 20 | AO11: 20
A12: 74451 | B12: 45TH STREET HOUSING PARTNERS LLC.PLP.FY25 | C12: 45835 | E12: 805625 | F12: 353 | G12: WEST 45 STREET | H12: Manhattan | I12: 10036 | J12: 1010360005 | K12: 1085018 | L12: MN-04 | M12: 3 | N12: 12101 | O12: MN0402 | P12: 40.759791 | Q12: -73.989868 | R12: 40.760279 | S12: -73.990463 | U12: Preservation | V12: No | W12: Non Prevailing Wage | X12: 4 | Y12: 14 | Z12: 2 | AE12: 10 | AF12: 10 | AL12: 20 | AN12: 20 | AO12: 20
A13: 74451 | B13: 45TH STREET HOUSING PARTNERS LLC.PLP.FY25 | C13: 45835 | E13: 805626 | F13: 355 | G13: WEST 45 STREET | H13: Manhattan | I13: 10036 | J13: 1010360005 | K13: 1085019 | L13: MN-04 | M13: 3 | N13: 12101 | O13: MN0402 | P13: 40.75981 | Q13: -73.989907 | R13: 40.760279 | S13: -73.990463 | U13: Preservation | V13: No | W13: Non Prevailing Wage | X13: 9 | Y13: 8 | Z13: 1 | AA13: 2 | AE13: 10 | AF13: 10 | AL13: 20 | AN13: 20 | AO13: 20
A14: 74487 | B14: MORNINGSIDE HEIGHTS II.HPO.FY25 | C14: 45835 | E14: 6068 | F14: 929 | G14: AMSTERDAM AVENUE | H14: Manhattan | I14: 10025 | J14: 1018600064 | K14: 1055946 | L14: MN-07 | M14: 7 | N14: 189 | O14: MN0703 | P14: 40.80012 | Q14: -73.965933 | R14: 40.79998 | S14: -73.96564 | U14: Preservation | V14: Yes | W14: Non Prevailing Wage | X14: 2 | Y14: 2 | Z14: 1 | AA14: 4 | AB14: 4 | AF14: 6 | AG14: 7 | AL14: 13 | AN14: 13 | AO14: 13
A15: 74487 | B15: MORNINGSIDE HEIGHTS II.HPO.FY25 | C15: 45835 | E15: 6070 | F15: 931 | G15: AMSTERDAM AVENUE | H15: Manhattan | I15: 10025 | J15: 1018600063 | K15: 1055945 | L15: MN-07 | M15: 7 | N15: 189 | O15: MN0703 | P15: 40.800175 | Q15: -73.965893 | R15: 40.80004 | S15: -73.965597 | U15: Preservation | V15: Yes | W15: Non Prevailing Wage | X15: 3 | Y15: 1 | Z15: 1 | AA15: 6 | AB15: 2 | AF15: 3 | AG15: 10 | AL15: 13 | AN15: 13 | AO15: 13
A16: 74487 | B16: MORNINGSIDE HEIGHTS II.HPO.FY25 | C16: 45835 | E16: 6072 | F16: 933 | G16: AMSTERDAM AVENUE | H16: Manhattan | I16: 10025 | J16: 1018600061 | K16: 1055944 | L16: MN-07 | M16: 7 | N16: 189 | O16: MN0703 | P16: 40.800227 | Q16: -73.965853 | R16: 40.800131 | S16: -73.965528 | U16: Preservation | V16: Yes | W16: Non Prevailing Wage | X16: 1 | Y16: 7 | Z16: 8 | AA16: 6 | AB16: 3 | AE16: 14 | AF16: 6 | AG16: 5 | AL16: 25 | AN16: 25 | AO16: 28
A17: 74487 | B17: MORNINGSIDE HEIGHTS II.HPO.FY25 | C17: 45835 | E17: 6090 | F17: 965 | G17: AMSTERDAM AVENUE | H17: Manhattan | I17: 10025 | J17: 1018620003 | K17: 1055985 | L17: MN-07 | M17: 7 | N17: 193 | O17: MN0703 | P17: 40.8013 | Q17: -73.965065 | R17: 40.801237 | S17: -73.964726 | U17: Preservation | V17: Yes | W17: Non Prevailing Wage | X17: 5 | Y17: 5 | AA17: 9 | AB17: 7 | AF17: 14 | AG17: 12 | AL17: 26 | AN17: 26 | AO17: 28
A18: 74487 | B18: MORNINGSIDE HEIGHTS II.HPO.FY25 | C18: 45835 | E18: 6092 | F18: 969 | G18: AMSTERDAM AVENUE | H18: Manhattan | I18: 10025 | J18: 1018620064 | K18: 1055995 | L18: MN-07 | M18: 7 | N18: 193 | O18: MN0703 | P18: 40.801399 | Q18: -73.964993 | R18: 40.801327 | S18: -73.964657 | U18: Preservation | V18: Yes | W18: Non Prevailing Wage | X18: 1 | Y18: 2 | Z18: 1 | AA18: 3 | AB18: 5 | AF18: 7 | AG18: 5 | AL18: 12 | AN18: 12 | AO18: 12
A19: 74487 | B19: MORNINGSIDE HEIGHTS II.HPO.FY25 | C19: 45835 | E19: 6093 | F19: 971 | G19: AMSTERDAM AVENUE | H19: Manhattan | I19: 10025 | J19: 1018620063 | K19: 1055994 | L19: MN-07 | M19: 7 | N19: 193 | O19: MN0703 | P19: 40.801445 | Q19: -73.96496 | R19: 40.801393 | S19: -73.964625 | U19: Preservation | V19: Yes | W19: Non Prevailing Wage | X19: 1 | Y19: 1 | Z19: 1 | AA19: 4 | AC19: 1 | AF19: 1 | AG19: 6 | AH19: 1 | AL19: 8 | AN19: 8 | AO19: 9
A20: 74487 | B20: MORNINGSIDE HEIGHTS II.HPO.FY25 | C20: 45835 | E20: 25200 | F20: 165 | G20: MANHATTAN AVENUE | H20: Manhattan | I20: 10025 | J20: 1018430017 | K20: 1055686 | L20: MN-07 | M20: 7 | N20: 193 | O20: MN0703 | P20: 40.799616 | Q20: -73.96079 | R20: 40.799858 | S20: -73.960967 | U20: Preservation | V20: Yes | W20: Non Prevailing Wage | Y20: 6 | Z20: 1 | AB20: 15 | AE20: 10 | AF20: 12 | AL20: 22 | AN20: 22 | AO20: 23
A21: 74487 | B21: MORNINGSIDE HEIGHTS II.HPO.FY25 | C21: 45835 | E21: 37515 | F21: 120 | G21: WEST 105 STREET | H21: Manhattan | I21: 10025 | J21: 1018590039 | K21: 1055924 | L21: MN-07 | M21: 7 | N21: 189 | O21: MN0703 | P21: 40.798821 | Q21: -73.96399 | R21: 40.798755 | S21: -73.96437 | U21: Preservation | V21: Yes | W21: Non Prevailing Wage | X21: 1 | Y21: 22 | Z21: 1 | AA21: 9 | AB21: 20 | AE21: 13 | AF21: 27 | AG21: 11 | AH21: 2 | AL21: 53 | AN21: 53 | AO21: 62
A22: 74487 | B22: MORNINGSIDE HEIGHTS II.HPO.FY25 | C22: 45835 | E22: 944847 | F22: 169 | G22: MANHATTAN AVENUE | H22: Manhattan | I22: 10025 | J22: 1018430051 | K22: 1055699 | L22: MN-07 | M22: 7 | N22: 193 | O22: MN0703 | P22: 40.799679 | Q22: -73.960743 | R22: 40.799959 | S22: -73.960894 | U22: Preservation | V22: Yes | W22: Non Prevailing Wage | Y22: 2 | AA22: 10 | AB22: 10 | AE22: 7 | AF22: 5 | AG22: 10 | AL22: 22 | AN22: 22 | AO22: 26
A23: 74974 | B23: MASARYK TOWERS.HRP.FY25 | C23: 45834 | E23: 9707 | F23: 51 | G23: COLUMBIA STREET | H23: Manhattan | I23: 10002 | J23: 1003330001 | K23: 1082667 | L23: MN-03 | M23: 2 | N23: 2201 | O23: MN0302 | P23: 40.716686 | Q23: -73.980463 | R23: 40.717885 | S23: -73.980845 | U23: Preservation | V23: No | W23: Non Prevailing Wage | X23: 1 | Y23: 218 | AD23: 20 | AE23: 40 | AF23: 139 | AG23: 20 | AM23: 219 | AN23: 219 | AO23: 219
A24: 74974 | B24: MASARYK TOWERS.HRP.FY25 | C24: 45834 | E24: 804199 | F24: 71 | G24: COLUMBIA STREET | H24: Manhattan | I24: 10002 | J24: 1003330001 | K24: 1082665 | L24: MN-03 | M24: 2 | N24: 2201 | O24: MN0302 | P24: 40.717218 | Q24: -73.980174 | R24: 40.717885 | S24: -73.980845 | U24: Preservation | V24: No | W24: Non Prevailing Wage | Y24: 208 | AD24: 1 | AE24: 20 | AF24: 145 | AG24: 42 | AM24: 208 | AN24: 208 | AO24: 208
A25: 74974 | B25: MASARYK TOWERS.HRP.FY25 | C25: 45834 | E25: 804200 | F25: 75 | G25: COLUMBIA STREET | H25: Manhattan | I25: 10002 | J25: 1003330001 | K25: 1082666 | L25: MN-03 | M25: 2 | N25: 2201 | O25: MN0302 | P25: 40.717567 | Q25: -73.979986 | R25: 40.717885 | S25: -73.980845 | U25: Preservation | V25: No | W25: Non Prevailing Wage | Y25: 350 | AD25: 20 | AE25: 81 | AF25: 186 | AG25: 63 | AM25: 350 | AN25: 350 | AO25: 350
A26: 74974 | B26: MASARYK TOWERS.HRP.FY25 | C26: 45834 | E26: 804201 | F26: 85 | G26: COLUMBIA STREET | H26: Manhattan | I26: 10002 | J26: 1003330001 | K26: 1086089 | L26: MN-03 | M26: 2 | N26: 2201 | O26: MN0302 | P26: 40.717891 | Q26: -73.979824 | R26: 40.717885 | S26: -73.980845 | U26: Preservation | V26: No | W26: Non Prevailing Wage | Y26: 331 | AC26: 1 | AD26: 1 | AE26: 60 | AF26: 187 | AG26: 84 | AM26: 332 | AN26: 332 | AO26: 332
A27: 73351 | B27: TMN302G 1772 SECOND AVENUE - PASSAGEWAY WORK | C27: 45833 | E27: 1067 | F27: 1772 | G27: 2 AVENUE | H27: Manhattan | I27: 10128 | J27: 1015550004 | K27: 1050240 | L27: MN-08 | M27: 5 | N27: 15402 | O27: MN0803 | P27: 40.7819 | Q27: -73.948798 | R27: 40.781839 | S27: -73.94844 | U27: Preservation | V27: No | W27: Non Prevailing Wage | X27: 13 | AE27: 9 | AF27: 4 | AL27: 13 | AN27: 13 | AO27: 13
A28: 77126 | B28: 205 CABRINI BLVD APARTMENTS | C28: 45827 | E28: 8787 | F28: 201 | G28: CABRINI BOULEVARD | H28: Manhattan | I28: 10033 | J28: 1021790152 | K28: 1000000 | L28: MN-12 | M28: 10 | N28: 273 | O28: MN1202 | P28: 40.854257 | Q28: -73.938953 | R28: 40.854202 | S28: -73.9387 | U28: New Construction | V28: No | W28: Non Prevailing Wage | AB28: 7 | AE28: 1 | AF28: 6 | AL28: 7 | AN28: 7 | AO28: 21
A29: 75525 | B29: GRAND ST. GUILD. 145 BROOME ST | C29: 45826 | E29: 1013038 | F29: 145 | G29: BROOME STREET | H29: Manhattan | I29: 10002 | J29: 1003410062 | K29: 1000000 | L29: MN-03 | M29: 1 | N29: 1402 | O29: MN0302 | P29: 40.716401 | Q29: -73.984582 | R29: 40.716231 | S29: -73.98504 | U29: New Construction | V29: No | W29: Prevailing Wage | X29: 190 | AC29: 1 | AD29: 87 | AE29: 103 | AF29: 1 | AL29: 191 | AN29: 191 | AO29: 191
A30: 75177 | B30: 170 EAST 83RD STREET.HPO.FY25 | C30: 45813 | E30: 1781 | F30: 170 | G30: EAST 83 STREET | H30: Manhattan | I30: 10028 | J30: 1015110033 | K30: 1047619 | L30: MN-08 | M30: 4 | N30: 140 | O30: MN0802 | P30: 40.777182 | Q30: -73.956174 | R30: 40.776847 | S30: -73.955936 | U30: Preservation | V30: No | W30: Non Prevailing Wage | X30: 1 | Y30: 2 | Z30: 12 | AA30: 21 | AB30: 5 | AC30: 9 | AD30: 11 | AE30: 12 | AF30: 14 | AG30: 13 | AL30: 50 | AN30: 50 | AO30: 50
A31: 75539 | B31: MCKENNA SQUARE APARTMENTS.HUDMF.FY25 | C31: 45807 | E31: 5774 | F31: 2101 | G31: AMSTERDAM AVENUE | H31: Manhattan | I31: 10032 | J31: 1021110001 | K31: 1079860 | L31: MN-12 | M31: 10 | N31: 24301 | O31: MN1201 | P31: 40.83733 | Q31: -73.938752 | R31: 40.837258 | S31: -73.938416 | U31: Preservation | V31: No | W31: Non Prevailing Wage | X31: 23 | Y31: 3 | Z31: 3 | AE31: 14 | AF31: 9 | AG31: 6 | AL31: 29 | AN31: 29 | AO31: 29
A32: 75539 | B32: MCKENNA SQUARE APARTMENTS.HUDMF.FY25 | C32: 45807 | E32: 6174 | F32: 11 | G32: AUDUBON AVENUE | H32: Manhattan | I32: 10032 | J32: 1021230030 | K32: 1079869 | L32: MN-12 | M32: 10 | N32: 251 | O32: MN1201 | P32: 40.839051 | Q32: -73.939383 | R32: 40.838991 | S32: -73.939097 | U32: Preservation | V32: No | W32: Non Prevailing Wage | X32: 31 | Y32: 2 | Z32: 3 | AD32: 1 | AE32: 23 | AF32: 1 | AG32: 11 | AL32: 36 | AN32: 36 | AO32: 36
A33: 75539 | B33: MCKENNA SQUARE APARTMENTS.HUDMF.FY25 | C33: 45807 | E33: 804009 | F33: 2134 | G33: AMSTERDAM AVENUE | H33: Manhattan | I33: 10032 | J33: 1021230038 | K33: 1079873 | L33: MN-12 | M33: 10 | N33: 251 | O33: MN1201 | P33: 40.838408 | Q33: -73.937992 | R33: 40.838589 | S33: -73.938299 | U33: Preservation | V33: No | W33: Non Prevailing Wage | X33: 31 | Y33: 4 | Z33: 2 | AA33: 1 | AC33: 1 | AD33: 5 | AE33: 10 | AF33: 19 | AG33: 5 | AL33: 39 | AN33: 39 | AO33: 39
A34: 76950 | B34: CONFIDENTIAL | C34: 45807 | D34: 45807 | F34: ---- | G34: ---- | H34: Manhattan | L34: MN-08 | M34: 5 | T34: 45807 | U34: New Construction | V34: No | W34: Non Prevailing Wage | Z34: 1 | AE34: 1 | AM34: 1 | AN34: 1 | AO34: 1
A35: 77109 | B35: 217 WEST 123RD STREET APARTMENTS | C35: 45803 | E35: 1017361 | F35: 217 | G35: WEST 123 STREET | H35: Manhattan | I35: 10027 | J35: 1019290023 | K35: 1058625 | L35: MN-10 | M35: 9 | N35: 222 | O35: MN1001 | P35: 40.808014 | Q35: -73.950078 | R35: 40.808239 | S35: -73.950052 | U35: New Construction | V35: No | W35: Non Prevailing Wage | AB35: 9 | AD35: 7 | AE35: 1 | AF35: 1 | AL35: 9 | AN35: 9 | AO35: 27
A36: 76205 | B36: 180 EAST 125TH STREET | C36: 45797 | E36: 1017430 | F36: 180 | G36: EAST 125 STREET | H36: Manhattan | I36: 10035 | J36: 1017730027 | K36: 1000000 | L36: MN-11 | M36: 8 | N36: 196 | O36: MN1102 | P36: 40.803942 | Q36: -73.936413 | R36: 40.803602 | S36: -73.936634 | U36: New Construction | V36: No | W36: Non Prevailing Wage | Z36: 85 | AD36: 29 | AE36: 40 | AF36: 16 | AL36: 85 | AN36: 85 | AO36: 614
A37: 76892 | B37: CONFIDENTIAL | C37: 45786 | D37: 45786 | F37: ---- | G37: ---- | H37: Manhattan | L37: MN-12 | M37: 10 | T37: 45786 | U37: New Construction | V37: No | W37: Non Prevailing Wage | Y37: 1 | AE37: 1 | AM37: 1 | AN37: 1 | AO37: 1
A38: 77172 | B38: WESTBETH | C38: 45778 | E38: 44252 | F38: 445 | G38: WEST STREET | H38: Manhattan | I38: 10014 | J38: 1006390001 | K38: 1012047 | L38: MN-02 | M38: 3 | N38: 79 | O38: MN0203 | P38: 40.736109 | Q38: -74.010013 | R38: 40.736529 | S38: -74.009075 | U38: Preservation | V38: No | W38: Non Prevailing Wage | Z38: 384 | AC38: 1 | AD38: 258 | AE38: 85 | AF38: 3 | AG38: 37 | AK38: 2 | AL38: 385 | AN38: 385 | AO38: 385
A39: 76819 | B39: CONFIDENTIAL | C39: 45765 | D39: 45765 | F39: ---- | G39: ---- | H39: Manhattan | L39: MN-06 | M39: 4 | T39: 45765 | U39: New Construction | V39: No | W39: Non Prevailing Wage | Z39: 1 | AD39: 1 | AM39: 1 | AN39: 1 | AO39: 1
A40: 77118 | B40: 1440 AMSTERDAM AVENUE | C40: 45762 | E40: 5561 | F40: 1440 | G40: AMSTERDAM AVENUE | H40: Manhattan | I40: 10027 | J40: 1019840028 | K40: 1091802 | L40: MN-09 | M40: 7 | N40: 219 | O40: MN0902 | P40: 40.81671 | Q40: -73.953847 | R40: 40.816771 | S40: -73.954251 | U40: New Construction | V40: No | W40: Non Prevailing Wage | AB40: 147 | AD40: 20 | AE40: 66 | AF40: 61 | AL40: 147 | AN40: 147 | AO40: 490
A41: 77117 | B41: 2903 FREDERICK DOUGLASS BLVD APARTMENTS | C41: 45756 | E41: 837174 | F41: 2903 | G41: FREDERICK DOUGLASS BOULEVARD | H41: Manhattan | I41: 10039 | J41: 1020470011 | K41: 1000000 | L41: MN-10 | M41: 9 | N41: 23502 | O41: MN1002 | P41: 40.828316 | Q41: -73.937929 | R41: 40.828349 | S41: -73.938294 | U41: New Construction | V41: No | W41: Non Prevailing Wage | AB41: 5 | AD41: 2 | AE41: 3 | AL41: 5 | AN41: 5 | AO41: 14
A42: 77062 | B42: 335 8TH AVENUE | C42: 45755 | E42: 975614 | F42: 323 | G42: 8 AVENUE | H42: Manhattan | I42: 10001 | J42: 1007510020 | K42: 1000000 | L42: MN-04 | M42: 3 | N42: 97 | O42: MN0401 | P42: 40.747303 | Q42: -73.997041 | R42: 40.747706 | S42: -73.997416 | U42: New Construction | V42: No | W42: Non Prevailing Wage | Z42: 19 | AB42: 38 | AD42: 18 | AE42: 31 | AF42: 8 | AL42: 57 | AN42: 57 | AO42: 188
A43: 77059 | B43: 1471 AMSTERDAM AVENUE | C43: 45751 | E43: 5572 | F43: 1471 | G43: AMSTERDAM AVENUE | H43: Manhattan | I43: 10027 | J43: 1019700064 | K43: 1059635 | L43: MN-09 | M43: 7 | N43: 21303 | O43: MN0902 | P43: 40.817336 | Q43: -73.953366 | R43: 40.817207 | S43: -73.95312 | U43: New Construction | V43: No | W43: Non Prevailing Wage | AB43: 3 | AE43: 3 | AL43: 3 | AN43: 3 | AO43: 9
A44: 77056 | B44: 1975 MADISON AVENUE | C44: 45750 | E44: 24774 | F44: 1971 | G44: MADISON AVENUE | H44: Manhattan | I44: 10035 | J44: 1017510020 | K44: 1000000 | L44: MN-11 | M44: 9 | N44: 206 | O44: MN1102 | P44: 40.806499 | Q44: -73.940077 | R44: 40.80643 | S44: -73.939654 | U44: New Construction | V44: No | W44: Non Prevailing Wage | AB44: 30 | AE44: 26 | AF44: 4 | AL44: 30 | AN44: 30 | AO44: 97
A45: 74709 | B45: 73 LOISAIDA HDFC.PLP.FY25 (73 AVENUE C) | C45: 45744 | E45: 6602 | F45: 73 | G45: AVENUE C | H45: Manhattan | I45: 10009 | J45: 1003870141 | K45: 1004658 | L45: MN-03 | M45: 2 | N45: 2601 | O45: MN0303 | P45: 40.722955 | Q45: -73.979692 | R45: 40.723172 | S45: -73.979865 | U45: Preservation | V45: No | W45: Non Prevailing Wage | Y45: 1 | Z45: 2 | AA45: 13 | AF45: 6 | AG45: 10 | AL45: 16 | AN45: 16 | AO45: 16
A46: 75990 | B46: 622 11TH AVENUE | C46: 45735 | E46: 1016882 | F46: 622 | G46: 11 AVENUE | H46: Manhattan | I46: 10036 | J46: 1010740063 | K46: 1026951 | L46: MN-04 | M46: 3 | N46: 12901 | O46: MN0402 | P46: 40.76317 | Q46: -73.996596 | R46: 40.762857 | S46: -73.996206 | U46: New Construction | V46: No | W46: Non Prevailing Wage | Z46: 22 | AD46: 4 | AE46: 5 | AF46: 13 | AL46: 22 | AN46: 22 | AO46: 98
A47: 76722 | B47: 185 CHRYSTIE STREET APARTMENTS | C47: 45734 | E47: 1009810 | F47: 185 | G47: CHRYSTIE STREET | H47: Manhattan | I47: 10002 | J47: 1004260035 | K47: 1000000 | L47: MN-03 | M47: 1 | N47: 3601 | O47: MN0302 | P47: 40.721611 | Q47: -73.992063 | R47: 40.721724 | S47: -73.992355 | U47: New Construction | V47: No | W47: Non Prevailing Wage | AB47: 11 | AE47: 4 | AF47: 7 | AL47: 11 | AN47: 11 | AO47: 40
A48: 76779 | B48: 555 WEST 45 STREET | C48: 45729 | E48: 5286 | F48: 616 | G48: 11 AVENUE | H48: Manhattan | I48: 10036 | J48: 1010740063 | K48: 1026951 | L48: MN-04 | M48: 3 | N48: 12901 | O48: MN0402 | P48: 40.763005 | Q48: -73.996715 | R48: 40.762857 | S48: -73.996206 | U48: New Construction | V48: No | W48: Non Prevailing Wage | Z48: 12 | AD48: 3 | AE48: 3 | AF48: 6 | AL48: 12 | AN48: 12 | AO48: 58
A49: 76765 | B49: 55 BROAD STREET | C49: 45722 | E49: 7525 | F49: 49 | G49: BROAD STREET | H49: Manhattan | I49: 10004 | J49: 1000250001 | K49: 1000821 | L49: MN-01 | M49: 1 | N49: 9 | O49: MN0101 | P49: 40.705357 | Q49: -74.01148 | R49: 40.705277 | S49: -74.011047 | U49: New Construction | V49: No | W49: Non Prevailing Wage | Y49: 29 | Z49: 76 | AA49: 38 | AD49: 70 | AE49: 63 | AF49: 9 | AG49: 1 | AL49: 143 | AN49: 143 | AO49: 571
A50: 75499 | B50: 142 WEST 139TH ST.HPO.FY25 | C50: 45707 | D50: 45707 | E50: 41291 | F50: 142 | G50: WEST 139 STREET | H50: Manhattan | I50: 10030 | J50: 1020070059 | K50: 1060050 | L50: MN-10 | M50: 9 | N50: 230 | O50: MN1002 | P50: 40.817591 | Q50: -73.941248 | R50: 40.817407 | S50: -73.941393 | T50: 45707 | U50: Preservation | V50: Yes | W50: Non Prevailing Wage | Y50: 1 | Z50: 11 | AA50: 8 | AE50: 20 | AL50: 20 | AN50: 20 | AO50: 20
A51: 76741 | B51: 280 8 AVENUE APARTMENTS | C51: 45706 | E51: 4343 | F51: 280 | G51: 8 AVENUE | H51: Manhattan | I51: 10001 | J51: 1007740001 | K51: 1000000 | L51: MN-04 | M51: 3 | N51: 91 | O51: MN0401 | P51: 40.746043 | Q51: -73.997928 | R51: 40.745977 | S51: -73.997542 | U51: New Construction | V51: No | W51: Non Prevailing Wage | AB51: 28 | AD51: 11 | AE51: 12 | AF51: 5 | AL51: 28 | AN51: 28 | AO51: 104
A52: 74863 | B52: TMN209G-1 644 RIVERSIDE (LOAN INCREASE) | C52: 45702 | E52: 27323 | F52: 644 | G52: RIVERSIDE DRIVE | H52: Manhattan | I52: 10031 | J52: 1020880114 | K52: 1062334 | L52: MN-09 | M52: 7 | N52: 225 | O52: MN0903 | P52: 40.82512 | Q52: -73.953892 | R52: 40.824988 | S52: -73.953584 | U52: Preservation | V52: No | W52: Non Prevailing Wage | Z52: 92 | AC52: 1 | AE52: 9 | AF52: 27 | AG52: 34 | AH52: 20 | AI52: 3 | AL52: 93 | AN52: 93 | AO52: 93
A53: 76562 | B53: CONFIDENTIAL | C53: 45702 | D53: 45702 | F53: ---- | G53: ---- | H53: Manhattan | L53: MN-09 | M53: 7 | T53: 45702 | U53: New Construction | V53: No | W53: Non Prevailing Wage | Z53: 1 | AF53: 1 | AM53: 1 | AN53: 1 | AO53: 1
A54: 70212 | B54: 534 3RD AVENUE | C54: 45699 | E54: 996025 | F54: 534 | G54: 3 AVENUE | H54: Manhattan | I54: 10016 | J54: 1008910044 | K54: 1000000 | L54: MN-06 | M54: 4 | N54: 80 | O54: MN0603 | P54: 40.74676 | Q54: -73.977383 | R54: 40.746941 | S54: -73.977628 | U54: New Construction | V54: No | W54: Non Prevailing Wage | Z54: 7 | AD54: 3 | AE54: 2 | AF54: 2 | AL54: 7 | AN54: 7 | AO54: 160
A55: 74296 | B55: SALEM HOUSE.YR15.FY25 | C55: 45687 | E55: 887513 | F55: 2185 | G55: ADAM C POWELL JR BOULEVARD | H55: Manhattan | I55: 10027 | J55: 1019147503 | K55: 1087836 | L55: MN-10 | M55: 9 | N55: 224 | O55: MN1002 | P55: 40.81164 | Q55: -73.946369 | R55: 40.811637 | S55: -73.945899 | U55: Preservation | V55: No | W55: Non Prevailing Wage | Y55: 44 | Z55: 2 | AA55: 1 | AC55: 1 | AE55: 19 | AF55: 23 | AG55: 6 | AL55: 48 | AN55: 48 | AO55: 48
A56: 76478 | B56: CONFIDENTIAL | C56: 45679 | D56: 45679 | F56: ---- | G56: ---- | H56: Manhattan | L56: MN-10 | M56: 9 | T56: 45679 | U56: New Construction | V56: No | W56: Non Prevailing Wage | Z56: 1 | AH56: 1 | AM56: 1 | AN56: 1 | AO56: 1
A57: 76751 | B57: 402 WEST 126 STREET APARTMENTS | C57: 45673 | E57: 978379 | F57: 402 | G57: WEST 126 STREET | H57: Manhattan | I57: 10027 | J57: 1019660077 | K57: 1000000 | L57: MN-09 | M57: 7 | N57: 20901 | O57: MN0901 | P57: 40.81211 | Q57: -73.953705 | R57: 40.812239 | S57: -73.95441 | U57: New Construction | V57: No | W57: Non Prevailing Wage | AB57: 28 | AD57: 7 | AE57: 7 | AF57: 14 | AL57: 28 | AN57: 28 | AO57: 93
A58: 77170 | B58: JERICHO HOUSE | C58: 45658 | E58: 3427 | F58: 2013 | G58: ADAM C POWELL BOULEVARD | H58: Manhattan | I58: 10027 | J58: 1019050063 | K58: 1057660 | L58: MN-10 | M58: 9 | N58: 220 | O58: MN1001 | P58: 40.806169 | Q58: -73.950361 | R58: 40.8061 | S58: -73.950054 | U58: Preservation | V58: No | W58: Non Prevailing Wage | X58: 56 | AD58: 56 | AL58: 56 | AN58: 56 | AO58: 56
A59: 76434 | B59: 463 WEST 125TH STREET APARTMENTS | C59: 45652 | D59: 45805 | E59: 1015652 | F59: 463 | G59: WEST 125 STREET | H59: Manhattan | I59: 10027 | J59: 1019660040 | K59: 1000000 | L59: MN-09 | M59: 7 | N59: 20901 | O59: MN0901 | P59: 40.812869 | Q59: -73.955807 | R59: 40.813159 | S59: -73.955659 | T59: 45805 | U59: New Construction | V59: No | W59: Non Prevailing Wage | AB59: 5 | AD59: 2 | AE59: 3 | AL59: 5 | AN59: 5 | AO59: 14
A60: 61846 | B60: PARK AVE - E 129 STREET CLUSTER | C60: 45650 | E60: 20832 | F60: 51 | G60: EAST 129 STREET | H60: Manhattan | I60: 10035 | J60: 1017540026 | K60: 1054235 | L60: MN-11 | M60: 9 | N60: 206 | O60: MN1102 | P60: 40.808096 | Q60: -73.938331 | R60: 40.808186 | S60: -73.937984 | U60: Preservation | V60: No | W60: Non Prevailing Wage | Y60: 20 | AA60: 10 | AE60: 1 | AG60: 13 | AH60: 16 | AM60: 30 | AN60: 30 | AO60: 30
A61: 61846 | B61: PARK AVE - E 129 STREET CLUSTER | C61: 45650 | E61: 26270 | F61: 1263 | G61: PARK AVENUE | H61: Manhattan | I61: 10029 | J61: 1016250072 | K61: 1051749 | L61: MN-11 | M61: 8 | N61: 15802 | O61: MN1101 | P61: 40.787585 | Q61: -73.951791 | R61: 40.787426 | S61: -73.951473 | U61: Preservation | V61: No | W61: Non Prevailing Wage | Y61: 7 | AA61: 3 | AF61: 10 | AM61: 10 | AN61: 10 | AO61: 10
A62: 61640 | B62: VINCENT P CYRUS.YR15.FY25 | C62: 45646 | E62: 829524 | F62: 57 | G62: EAST 128 STREET | H62: Manhattan | I62: 10035 | J62: 1017530027 | K62: 1087343 | L62: MN-11 | M62: 9 | N62: 206 | O62: MN1102 | P62: 40.807421 | Q62: -73.938667 | R62: 40.807462 | S62: -73.938201 | U62: Preservation | V62: No | W62: Prevailing Wage | X62: 39 | Y62: 1 | Z62: 3 | AD62: 43 | AL62: 43 | AN62: 43 | AO62: 43
A63: 61640 | B63: VINCENT P CYRUS.YR15.FY25 | C63: 45646 | E63: 831968 | F63: 73 | G63: EAST 128 STREET | H63: Manhattan | I63: 10035 | J63: 1017530027 | K63: 1090911 | L63: MN-11 | M63: 9 | N63: 206 | O63: MN1102 | P63: 40.807311 | Q63: -73.938411 | R63: 40.807462 | S63: -73.938201 | U63: Preservation | V63: No | W63: Prevailing Wage | X63: 45 | Y63: 10 | Z63: 5 | AC63: 1 | AD63: 60 | AE63: 1 | AL63: 61 | AN63: 61 | AO63: 61
A64: 70595 | B64: RENAISSANCE HDFC.HPO.FY25 | C64: 45646 | E64: 818428 | F64: 120 | G64: LENOX AVENUE | H64: Manhattan | I64: 10026 | J64: 1016007501 | K64: 1085936 | L64: MN-04 | M64: 9 | N64: 190 | O64: MN1001 | P64: 40.802162 | Q64: -73.949569 | R64: 40.802029 | S64: -73.948511 | U64: Preservation | V64: No | W64: Non Prevailing Wage | Y64: 11 | Z64: 182 | AA64: 44 | AB64: 3 | AC64: 1 | AE64: 9 | AF64: 144 | AG64: 88 | AM64: 241 | AN64: 241 | AO64: 241
A65: 76349 | B65: 25 WATER STREET | C65: 45646 | E65: 7514 | F65: 25 | G65: WATER STREET | H65: Manhattan | I65: 10004 | J65: 1000050010 | K65: 1000007 | L65: MN-01 | M65: 1 | N65: 9 | O65: MN0101 | P65: 40.703026 | Q65: -74.011202 | R65: 40.702777 | S65: -74.010722 | U65: New Construction | V65: No | W65: Non Prevailing Wage | Y65: 66 | Z65: 4 | AA65: 260 | AD65: 238 | AE65: 73 | AF65: 12 | AG65: 7 | AL65: 330 | AN65: 330 | AO65: 1320
A66: 71443 | B66: FORTUNE SOCIETY. 256-258 WEST 97TH ST | C66: 45645 | E66: 37262 | F66: 256 | G66: WEST 97 STREET | H66: Manhattan | I66: 10025 | J66: 1018680059 | K66: 1056065 | L66: MN-07 | M66: 7 | N66: 183 | O66: MN0702 | P66: 40.795574 | Q66: -73.971898 | R66: 40.795508 | S66: -73.972302 | U66: Preservation | V66: No | W66: Non Prevailing Wage | X66: 80 | Z66: 3 | AC66: 1 | AD66: 84 | AL66: 84 | AN66: 84 | AO66: 84
A67: 73533 | B67: PETER JAY SHARP.YR15.FY25 | C67: 45645 | E67: 866098 | F67: 223 | G67: EAST 117 STREET | H67: Manhattan | I67: 10035 | J67: 1016670012 | K67: 1085963 | L67: MN-11 | M67: 8 | N67: 188 | O67: MN1102 | P67: 40.798344 | Q67: -73.938827 | R67: 40.798313 | S67: -73.938202 | U67: Preservation | V67: No | W67: Prevailing Wage | X67: 56 | Y67: 11 | Z67: 4 | AA67: 2 | AC67: 1 | AD67: 74 | AL67: 74 | AN67: 74 | AO67: 74
A68: 75409 | B68: BG. 1760 THIRD AVE - CONSTRUCTION CLOSING | C68: 45645 | E68: 1886 | F68: 1768 | G68: 3 AVENUE | H68: Manhattan | I68: 10029 | J68: 1016250033 | K68: 1051738 | L68: MN-11 | M68: 8 | N68: 15802 | O68: MN1101 | P68: 40.786368 | Q68: -73.948476 | R68: 40.786313 | S68: -73.948924 | U68: Preservation | V68: No | W68: Non Prevailing Wage | X68: 261 | Z68: 172 | AC68: 1 | AD68: 388 | AE68: 45 | AF68: 1 | AL68: 434 | AN68: 434 | AO68: 434
A69: 75549 | B69: MORNINGSIDE I.HUDMF.FY25 | C69: 45645 | D69: 45645 | E69: 25538 | F69: 20 | G69: MORNINGSIDE AVENUE | H69: Manhattan | I69: 10026 | J69: 1019430001 | K69: 1081519 | L69: MN-10 | M69: 9 | N69: 20102 | O69: MN1001 | P69: 40.805708 | Q69: -73.95811 | R69: 40.805656 | S69: -73.957568 | T69: 45645 | U69: Preservation | V69: Yes | W69: Non Prevailing Wage | X69: 39 | Y69: 5 | Z69: 2 | AB69: 6 | AC69: 1 | AD69: 2 | AE69: 28 | AF69: 15 | AG69: 7 | AH69: 1 | AL69: 53 | AN69: 53 | AO69: 53
A70: 75549 | B70: MORNINGSIDE I.HUDMF.FY25 | C70: 45645 | D70: 45645 | E70: 805872 | F70: 369 | G70: WEST 116 STREET | H70: Manhattan | I70: 10026 | J70: 1019430001 | K70: 1081516 | L70: MN-10 | M70: 9 | N70: 20102 | O70: MN1001 | P70: 40.805277 | Q70: -73.95738 | R70: 40.805656 | S70: -73.957568 | T70: 45645 | U70: Preservation | V70: Yes | W70: Non Prevailing Wage | X70: 39 | Y70: 11 | Z70: 4 | AB70: 2 | AE70: 15 | AF70: 41 | AL70: 56 | AN70: 56 | AO70: 56
A71: 72745 | B71: THE BRIDGE. 39 WEST 128 STREET | C71: 45644 | E71: 1004751 | F71: 37 | G71: WEST 128 STREET | H71: Manhattan | I71: 10027 | L71: MN-10 | M71: 9 | N71: 208 | O71: MN1002 | P71: 40.80888 | Q71: -73.94213 | U71: New Construction | V71: No | W71: Non Prevailing Wage | X71: 86 | Z71: 5 | AC71: 1 | AD71: 75 | AE71: 16 | AF71: 1 | AL71: 92 | AN71: 92 | AO71: 92
A72: 75051 | B72: CATHEDRAL PARKWAY & MID-HARLEM.YR15.FY25 | C72: 45644 | D72: 45644 | E72: 3494 | F72: 2246 | G72: ADAM C POWELL BOULEVARD | H72: Manhattan | I72: 10027 | J72: 1019380030 | K72: 1058779 | L72: MN-10 | M72: 9 | N72: 226 | O72: MN1002 | P72: 40.813547 | Q72: -73.944998 | R72: 40.813709 | S72: -73.945374 | T72: 45644 | U72: Preservation | V72: Yes | W72: Non Prevailing Wage | X72: 3 | Y72: 3 | Z72: 1 | AA72: 1 | AE72: 4 | AF72: 4 | AL72: 8 | AN72: 8 | AO72: 8
A73: 75051 | B73: CATHEDRAL PARKWAY & MID-HARLEM.YR15.FY25 | C73: 45644 | D73: 45644 | E73: 3594 | F73: 2423 | G73: ADAM C POWELL BOULEVARD | H73: Manhattan | I73: 10030 | J73: 1020100064 | K73: 1060100 | L73: MN-10 | M73: 9 | N73: 230 | O73: MN1002 | P73: 40.819375 | Q73: -73.940716 | R73: 40.81924 | S73: -73.940318 | T73: 45644 | U73: Preservation | V73: Yes | W73: Non Prevailing Wage | X73: 2 | Y73: 7 | Z73: 2 | AD73: 1 | AF73: 5 | AG73: 5 | AL73: 11 | AN73: 11 | AO73: 11
A74: 75051 | B74: CATHEDRAL PARKWAY & MID-HARLEM.YR15.FY25 | C74: 45644 | D74: 45644 | E74: 3917 | F74: 2084 | G74: FREDERICK DOUGLASS BOULEVARD | H74: Manhattan | I74: 10026 | J74: 1018280061 | K74: 1055127 | L74: MN-10 | M74: 9 | N74: 216 | O74: MN1001 | P74: 40.802299 | Q74: -73.956902 | R74: 40.802258 | S74: -73.956537 | T74: 45644 | U74: Preservation | V74: Yes | W74: Non Prevailing Wage | X74: 1 | Y74: 2 | Z74: 3 | AA74: 3 | AF74: 1 | AG74: 8 | AL74: 9 | AN74: 9 | AO74: 9
A75: 75051 | B75: CATHEDRAL PARKWAY & MID-HARLEM.YR15.FY25 | C75: 45644 | D75: 45644 | E75: 37867 | F75: 212 | G75: WEST 111 STREET | H75: Manhattan | I75: 10026 | J75: 1018260044 | K75: 1055070 | L75: MN-10 | M75: 9 | N75: 216 | O75: MN1001 | P75: 40.800333 | Q75: -73.955588 | R75: 40.800301 | S75: -73.956105 | T75: 45644 | U75: Preservation | V75: Yes | W75: Non Prevailing Wage | X75: 1 | Y75: 9 | Z75: 2 | AA75: 8 | AB75: 1 | AD75: 2 | AE75: 13 | AF75: 3 | AG75: 3 | AL75: 21 | AN75: 21 | AO75: 21
A76: 75051 | B76: CATHEDRAL PARKWAY & MID-HARLEM.YR15.FY25 | C76: 45644 | D76: 45644 | E76: 37869 | F76: 216 | G76: WEST 111 STREET | H76: Manhattan | I76: 10026 | J76: 1018260046 | K76: 1055071 | L76: MN-10 | M76: 9 | N76: 216 | O76: MN1001 | P76: 40.800366 | Q76: -73.955668 | R76: 40.800367 | S76: -73.95626 | T76: 45644 | U76: Preservation | V76: Yes | W76: Non Prevailing Wage | X76: 2 | Y76: 8 | Z76: 3 | AA76: 7 | AC76: 1 | AD76: 1 | AE76: 14 | AF76: 3 | AG76: 3 | AL76: 21 | AN76: 21 | AO76: 21
A77: 75051 | B77: CATHEDRAL PARKWAY & MID-HARLEM.YR15.FY25 | C77: 45644 | D77: 45644 | E77: 38041 | F77: 267 | G77: WEST 113 STREET | H77: Manhattan | I77: 10026 | J77: 1018290009 | K77: 1055141 | L77: MN-10 | M77: 9 | N77: 216 | O77: MN1001 | P77: 40.802087 | Q77: -73.955811 | R77: 40.802334 | S77: -73.955836 | T77: 45644 | U77: Preservation | V77: Yes | W77: Non Prevailing Wage | Y77: 4 | Z77: 1 | AA77: 7 | AE77: 5 | AF77: 3 | AG77: 4 | AL77: 12 | AN77: 12 | AO77: 12
A78: 75051 | B78: CATHEDRAL PARKWAY & MID-HARLEM.YR15.FY25 | C78: 45644 | D78: 45644 | E78: 38050 | F78: 280 | G78: WEST 113 STREET | H78: Manhattan | I78: 10026 | J78: 1018280060 | K78: 1055126 | L78: MN-10 | M78: 9 | N78: 216 | O78: MN1001 | P78: 40.802216 | Q78: -73.956161 | R78: 40.802082 | S78: -73.956407 | T78: 45644 | U78: Preservation | V78: Yes | W78: Non Prevailing Wage | X78: 1 | Y78: 4 | Z78: 3 | AA78: 6 | AC78: 1 | AE78: 10 | AF78: 4 | AG78: 1 | AL78: 15 | AN78: 15 | AO78: 15
A79: 75051 | B79: CATHEDRAL PARKWAY & MID-HARLEM.YR15.FY25 | C79: 45644 | D79: 45644 | E79: 38234 | F79: 225 | G79: WEST 115 STREET | H79: Manhattan | I79: 10026 | J79: 1018310116 | K79: 1055251 | L79: MN-10 | M79: 9 | N79: 218 | O79: MN1001 | P79: 40.803067 | Q79: -73.954257 | R79: 40.803322 | S79: -73.9543 | T79: 45644 | U79: Preservation | V79: Yes | W79: Non Prevailing Wage | Y79: 2 | Z79: 1 | AA79: 2 | AF79: 5 | AL79: 5 | AN79: 5 | AO79: 5
A80: 75051 | B80: CATHEDRAL PARKWAY & MID-HARLEM.YR15.FY25 | C80: 45644 | D80: 45644 | E80: 38238 | F80: 235 | G80: WEST 115 STREET | H80: Manhattan | I80: 10026 | J80: 1018310012 | K80: 1055227 | L80: MN-10 | M80: 9 | N80: 218 | O80: MN1001 | P80: 40.803284 | Q80: -73.954759 | R80: 40.803484 | S80: -73.954661 | T80: 45644 | U80: Preservation | V80: Yes | W80: Non Prevailing Wage | X80: 2 | Y80: 1 | Z80: 3 | AA80: 4 | AE80: 5 | AF80: 5 | AL80: 10 | AN80: 10 | AO80: 10
A81: 75051 | B81: CATHEDRAL PARKWAY & MID-HARLEM.YR15.FY25 | C81: 45644 | D81: 45644 | E81: 40656 | F81: 231 | G81: WEST 134 STREET | H81: Manhattan | I81: 10030 | J81: 1019400019 | K81: 1058832 | L81: MN-10 | M81: 9 | N81: 228 | O81: MN1002 | P81: 40.815098 | Q81: -73.945271 | R81: 40.815332 | S81: -73.945275 | T81: 45644 | U81: Preservation | V81: Yes | W81: Non Prevailing Wage | Y81: 1 | Z81: 1 | AA81: 2 | AB81: 1 | AE81: 2 | AF81: 3 | AL81: 5 | AN81: 5 | AO81: 5
A82: 75051 | B82: CATHEDRAL PARKWAY & MID-HARLEM.YR15.FY25 | C82: 45644 | D82: 45644 | E82: 40745 | F82: 241 | G82: WEST 135 STREET | H82: Manhattan | I82: 10030 | J82: 1019410008 | K82: 1058875 | L82: MN-10 | M82: 9 | N82: 228 | O82: MN1002 | P82: 40.816194 | Q82: -73.945787 | R82: 40.816427 | S82: -73.945621 | T82: 45644 | U82: Preservation | V82: Yes | W82: Non Prevailing Wage | Y82: 4 | Z82: 3 | AA82: 2 | AB82: 1 | AD82: 1 | AE82: 5 | AF82: 4 | AL82: 10 | AN82: 10 | AO82: 10
A83: 75051 | B83: CATHEDRAL PARKWAY & MID-HARLEM.YR15.FY25 | C83: 45644 | D83: 45644 | E83: 41097 | F83: 67 | G83: WEST 137 STREET | H83: Manhattan | I83: 10037 | J83: 1017350006 | K83: 1053902 | L83: MN-10 | M83: 9 | N83: 212 | O83: MN1002 | P83: 40.814878 | Q83: -73.938639 | R83: 40.815326 | S83: -73.93914 | T83: 45644 | U83: Preservation | V83: Yes | W83: Non Prevailing Wage | X83: 3 | Y83: 6 | Z83: 2 | AA83: 1 | AB83: 1 | AC83: 1 | AD83: 1 | AE83: 5 | AG83: 8 | AL83: 14 | AN83: 14 | AO83: 14
A84: 76200 | B84: CONFIDENTIAL | C84: 45639 | D84: 45639 | F84: ---- | G84: ---- | H84: Manhattan | L84: MN-06 | M84: 4 | T84: 45639 | U84: New Construction | V84: No | W84: Non Prevailing Wage | Z84: 1 | AE84: 1 | AM84: 1 | AN84: 1 | AO84: 1
A85: 73472 | B85: 185 CHRYSTIE STREET | C85: 45638 | E85: 1009810 | F85: 185 | G85: CHRYSTIE STREET | H85: Manhattan | I85: 10002 | J85: 1004260035 | K85: 1000000 | L85: MN-03 | M85: 1 | N85: 3601 | O85: MN0302 | P85: 40.721611 | Q85: -73.992063 | R85: 40.721724 | S85: -73.992355 | U85: New Construction | V85: No | W85: Non Prevailing Wage | Y85: 4 | Z85: 7 | AE85: 4 | AF85: 7 | AL85: 11 | AN85: 11 | AO85: 58
A86: 76207 | B86: CONFIDENTIAL | C86: 45638 | D86: 45638 | F86: ---- | G86: ---- | H86: Manhattan | L86: MN-04 | M86: 3 | T86: 45638 | U86: New Construction | V86: No | W86: Non Prevailing Wage | Z86: 1 | AD86: 1 | AM86: 1 | AN86: 1 | AO86: 1
A87: 75374 | B87: UPACA / 1900 LEXINGTON.YR15.FY25 | C87: 45637 | D87: 45637 | E87: 24078 | F87: 1900 | G87: LEXINGTON AVENUE | H87: Manhattan | I87: 10035 | J87: 1017670016 | K87: 1054347 | L87: MN-11 | M87: 9 | N87: 182 | O87: MN1102 | P87: 40.800055 | Q87: -73.940585 | R87: 40.800349 | S87: -73.940733 | T87: 45637 | U87: Preservation | V87: Yes | W87: Non Prevailing Wage | X87: 86 | Y87: 20 | Z87: 12 | AA87: 14 | AB87: 1 | AC87: 1 | AD87: 1 | AE87: 4 | AF87: 97 | AG87: 32 | AL87: 134 | AN87: 134 | AO87: 134
A88: 76424 | B88: MAISON78 | C88: 45635 | E88: 1008972 | F88: 1487 | G88: 1 AVENUE | H88: Manhattan | I88: 10075 | J88: 1014520027 | K88: 1000000 | L88: MN-08 | M88: 5 | N88: 134 | O88: MN0801 | P88: 40.771378 | Q88: -73.953405 | R88: 40.771595 | S88: -73.953636 | U88: New Construction | V88: No | W88: Non Prevailing Wage | AB88: 45 | AD88: 8 | AE88: 14 | AF88: 23 | AL88: 45 | AN88: 45 | AO88: 146
A89: 74485 | B89: RACHEL BRIDGE HDFC.HPO.FY25 | C89: 45623 | D89: 45623 | E89: 27974 | F89: 1360 | G89: ST NICHOLAS AVENUE | H89: Manhattan | I89: 10033 | J89: 1021530001 | K89: 1079909 | L89: MN-12 | M89: 10 | N89: 261 | O89: MN1201 | P89: 40.847503 | Q89: -73.935052 | R89: 40.84739 | S89: -73.93421 | T89: 45623 | U89: Preservation | V89: Yes | W89: Non Prevailing Wage | Y89: 22 | Z89: 158 | AA89: 59 | AB89: 1 | AD89: 60 | AE89: 60 | AG89: 120 | AL89: 240 | AN89: 240 | AO89: 240
A90: 74485 | B90: RACHEL BRIDGE HDFC.HPO.FY25 | C90: 45623 | D90: 45623 | E90: 28980 | F90: 101 | G90: WADSWORTH AVENUE | H90: Manhattan | I90: 10033 | J90: 1021620001 | K90: 1079921 | L90: MN-12 | M90: 10 | N90: 263 | O90: MN1201 | P90: 40.848099 | Q90: -73.936215 | R90: 40.84795 | S90: -73.935561 | T90: 45623 | U90: Preservation | V90: Yes | W90: Non Prevailing Wage | Y90: 17 | Z90: 167 | AA90: 54 | AB90: 2 | AE90: 60 | AF90: 180 | AL90: 240 | AN90: 240 | AO90: 240
A91: 74485 | B91: RACHEL BRIDGE HDFC.HPO.FY25 | C91: 45623 | D91: 45623 | E91: 804020 | F91: 258 | G91: AUDUBON AVENUE | H91: Manhattan | I91: 10033 | J91: 1021530001 | K91: 1079908 | L91: MN-12 | M91: 10 | N91: 261 | O91: MN1201 | P91: 40.847043 | Q91: -73.933585 | R91: 40.84739 | S91: -73.93421 | T91: 45623 | U91: Preservation | V91: Yes | W91: Non Prevailing Wage | Y91: 7 | Z91: 187 | AA91: 44 | AB91: 1 | AC91: 1 | AE91: 60 | AF91: 180 | AL91: 240 | AN91: 240 | AO91: 240
A92: 74485 | B92: RACHEL BRIDGE HDFC.HPO.FY25 | C92: 45623 | D92: 45623 | E92: 805325 | F92: 1361 | G92: ST NICHOLAS AVENUE | H92: Manhattan | I92: 10033 | J92: 1021620001 | K92: 1079920 | L92: MN-12 | M92: 10 | N92: 263 | O92: MN1201 | P92: 40.847511 | Q92: -73.93507 | R92: 40.84795 | S92: -73.935561 | T92: 45623 | U92: Preservation | V92: Yes | W92: Non Prevailing Wage | Y92: 27 | Z92: 158 | AA92: 54 | AC92: 1 | AD92: 60 | AE92: 60 | AG92: 120 | AL92: 240 | AN92: 240 | AO92: 240
A93: 76387 | B93: 88 MARBLE HILL AVENUE | C93: 45618 | E93: 25381 | F93: 86 | G93: MARBLE HILL AVENUE | H93: Manhattan | I93: 10463 | J93: 1022150569 | K93: 1000000 | L93: MN-12 | M93: 10 | N93: 309 | O93: BX0802 | P93: 40.876661 | Q93: -73.909444 | R93: 40.876598 | S93: -73.909187 | U93: New Construction | V93: No | W93: Non Prevailing Wage | AB93: 3 | AE93: 3 | AL93: 3 | AN93: 3 | AO93: 8
A94: 76387 | B94: 88 MARBLE HILL AVENUE | C94: 45618 | E94: 1015678 | F94: 88 | G94: MARBLE HILL AVENUE | H94: Manhattan | I94: 10463 | J94: 1022150569 | K94: 1000000 | L94: MN-12 | M94: 10 | N94: 309 | O94: BX0802 | P94: 40.876705 | Q94: -73.909429 | R94: 40.876598 | S94: -73.909187 | U94: New Construction | V94: No | W94: Non Prevailing Wage | AB94: 3 | AE94: 3 | AL94: 3 | AN94: 3 | AO94: 8
A95: 67035 | B95: LAS RAICES | C95: 45604 | E95: 1002396 | F95: 1761 | G95: PARK AVENUE | H95: Manhattan | I95: 10035 | J95: 1017710001 | K95: 1000000 | L95: MN-11 | M95: 9 | N95: 196 | O95: MN1102 | P95: 40.803258 | Q95: -73.940329 | R95: 40.803101 | S95: -73.939997 | U95: New Construction | V95: No | W95: Non Prevailing Wage | X95: 8 | Y95: 21 | Z95: 17 | AC95: 1 | AD95: 10 | AE95: 22 | AF95: 15 | AL95: 47 | AN95: 47 | AO95: 47
A96: 67035 | B96: LAS RAICES | C96: 45604 | E96: 1008959 | F96: 507 | G96: EAST 118 STREET | H96: Manhattan | I96: 10035 | J96: 1018150006 | K96: 1000000 | L96: MN-11 | M96: 8 | N96: 178 | O96: MN1102 | P96: 40.796273 | Q96: -73.931978 | R96: 40.796317 | S96: -73.931512 | U96: New Construction | V96: No | W96: Non Prevailing Wage | X96: 2 | Y96: 8 | Z96: 8 | AD96: 5 | AE96: 6 | AF96: 4 | AG96: 3 | AL96: 18 | AN96: 18 | AO96: 18
A97: 67035 | B97: LAS RAICES | C97: 45604 | E97: 1011929 | F97: 338 | G97: EAST 117 STREET | H97: Manhattan | I97: 10035 | J97: 1016880034 | K97: 1000000 | L97: MN-11 | M97: 8 | N97: 188 | O97: MN1102 | P97: 40.797165 | Q97: -73.93608 | R97: 40.796772 | S97: -73.935719 | U97: New Construction | V97: No | W97: Non Prevailing Wage | X97: 1 | Y97: 4 | Z97: 2 | AD97: 1 | AE97: 4 | AG97: 2 | AL97: 7 | AN97: 7 | AO97: 7
A98: 67035 | B98: LAS RAICES | C98: 45604 | E98: 1011930 | F98: 303 | G98: EAST 102 STREET | H98: Manhattan | I98: 10029 | J98: 1016740104 | K98: 1091726 | L98: MN-11 | M98: 8 | N98: 164 | O98: MN1101 | P98: 40.788016 | Q98: -73.944199 | R98: 40.788043 | S98: -73.943759 | U98: New Construction | V98: No | W98: Non Prevailing Wage | X98: 1 | Y98: 4 | Z98: 1 | AD98: 4 | AF98: 2 | AL98: 6 | AN98: 6 | AO98: 6
A99: 76149 | B99: CONFIDENTIAL | C99: 45604 | F99: ---- | G99: ---- | H99: Manhattan | L99: MN-10 | M99: 9 | U99: Preservation | V99: No | W99: Non Prevailing Wage | Z99: 4 | AK99: 4 | AM99: 4 | AN99: 4 | AO99: 4
A100: 76168 | B100: CONFIDENTIAL | C100: 45604 | F100: ---- | G100: ---- | H100: Manhattan | L100: MN-10 | M100: 9 | U100: Preservation | V100: No | W100: Non Prevailing Wage | Z100: 4 | AK100: 4 | AM100: 4 | AN100: 4 | AO100: 4
...

Sheet HNY_CB1_raw1
A1: Project Name | B1: Borough | C1: Community Board | D1: Extremely Low Income Units | E1: Very Low Income Units | F1: Low Income Units | G1: Moderate Income Units | H1: Middle Income Units | I1: Other Income Units | J1: Total Units
A2: 55 BROAD STREET | B2: Manhattan | C2: MN-01 | E2: 29 | F2: 76 | G2: 38 | J2: =SUM(D2:I2) -> 143
A3: 25 WATER STREET | B3: Manhattan | C3: MN-01 | E3: 66 | F3: 4 | G3: 260 | J3: =SUM(D3:I3) -> 330
A4: 7 DEY STREET | B4: Manhattan | C4: MN-01 | F4: 21 | H4: 42 | J4: =SUM(D4:I4) -> 63
A5: EVERLASTING PINES HDFC | B5: Manhattan | C5: MN-01 | D5: 86 | E5: 1 | I5: 1 | J5: =SUM(D5:I5) -> 88
A6: 118 Fulton Street | B6: Manhattan | C6: MN-01 | F6: 97 | J6: =SUM(D6:I6) -> 97
A7: 56 FULTON STREET | B7: Manhattan | C7: MN-01 | E7: 12 | F7: 12 | H7: 6 | J7: =SUM(D7:I7) -> 30
A8: 456 Washington Street | B8: Manhattan | C8: MN-01 | F8: 22
E15: Extremely Low = 30% AMI
E17: Very Low = 40% AMI
E19: Low = 60% AMI
E21: Moderate = 80% AMI
E23: Middle = 120% AMI

Sheet SUMMARY - FINAL 
A1: Area Median Income (AMI)
A2: Family Size | B2: 0.3 | C2: 0.4 | D2: 0.5 | E2: 0.6 | F2: 0.7 | G2: 0.8 | H2: 0.9 | I2: 1 | J2: 1.1 | K2: 1.2 | L2: 1.3 | M2: 1.65 | Q2: AMI_Level | R2: Required_Income_3Person | S2: Units_Built
A3: 1 | B3: 34020 | C3: 45360 | D3: 56700 | E3: 68040 | F3: 79380 | G3: 90720 | H3: 102060 | I3: 113400 | J3: 124740 | K3: 136080 | L3: 147420 | M3: 187110
A4: 2 | B4: 38880 | C4: 51840 | D4: 64800 | E4: 77760 | F4: 90720 | G4: 103680 | H4: 116640 | I4: 129600 | J4: 142560 | K4: 155520 | L4: 168480 | M4: 213840
A5: Required Income 3 Person | B5: 43740 | C5: 58320 | D5: 72900 | E5: 87480 | F5: 102060 | G5: 116640 | H5: 131220 | I5: 145800 | J5: 160380 | K5: 174960 | L5: 189540 | M5: 240570 | P5: Extremely Low-Income | Q5: 0-30% | S5: 86
A6: Units Built | B6: =Summary!B2 -> 86 | D6: =Summary!B3 -> 108 | G6: =Summary!B4 -> 232 | K6: =Summary!B5 -> 298 | M6: =Summary!B6 -> 48 | P6: Very Low-Income | Q6: 31-50% | S6: 108
P7: Low-Income | Q7: 51-80% | S7: 232
P8: Moderate-Income | Q8: 81-120% | S8: 298
A9: Income Band | B9: Percent of AMI | P9: Middle-Income | Q9: 121-165% | S9: 48
A10: Extremely Low-Income | B10: 0-30%
A11: Very Low-Income | B11: 31-50%
A12: Low-Income | B12: 51-80%
A13: Moderate-Income | B13: 81-120%
A14: Middle-Income | B14: 121-165%
A17: Sources:
A18: Area Median Income - HPD
A19: Affordable Housing Production by Project | NYC Open Data

Sheet CB_income
A1: Community_Board | B1: Median_Household_income
A2: 101 | B2: 198945

Sheet AMI_referenc xe
A1: AMI_Level | B1: Required_Income_1_Person | C1: Required_Income_2_Person | D1: Required_Income_3_Person | E1: Required_Income_4_Person
A2: 0.3 | B2: $34,020 | C2: 38880 | D2: $43,740 | E2: 48600
A3: 0.4 | B3: 45360 | C3: $51,840 | D3: 58320 | E3: 64800
A4: 0.5 | B4: 56700 | C4: $64,800 | D4: 72900 | E4: 81000
A5: 0.6 | B5: $68,040 | C5: 77760 | D5: 87480 | E5: 97200
A6: 0.7 | B6: 79380 | C6: $90,720 | D6: $102,060 | E6: 113400
A7: 0.8 | B7: 90720 | C7: 103680 | D7: 116640 | E7: $129,600
A8: 0.9 | B8: $102,060 | C8: 116640 | D8: 131220 | E8: 145800
A9: 1 | B9: 113400 | C9: $129,600 | D9: 145800 | E9: 162000
A10: 1.1 | B10: 124740 | C10: 142560 | D10: 160380 | E10: 178200
A11: 1.2 | B11: 136080 | C11: 155520 | D11: 174960 | E11: 194400
A12: 1.3
A13: 1.65

Sheet AMI_reference 
A1: AMI_Level | B1: Required_Income_1_Person | C1: Required_Income_2_Person | D1: Required_Income_3_Person | E1: Required_Income_4_Person
A2: 0.3 | B2: 34020 | C2: 38880 | D2: 43740 | E2: 48600
A3: 0.4 | B3: 45360 | C3: 51840 | D3: 58320 | E3: 64800 | G3: read definitions
A4: 0.6 | B4: 68040 | C4: 77760 | D4: 87480 | E4: 97200
A5: 0.8 | B5: 90720 | C5: 103680 | D5: 116640 | E5: 129600
A6: 1.2 | B6: 136080 | C6: 155520 | D6: 174960 | E6: 194400

Sheet Summary
A1: AMI_Level | B1: Total_Units | C1: Median_Income | D1: Req_Income_1 | E1: Req_Income_2 | F1: Req_Income_3 | G1: Req_Income_4 | H1: Gap_1 | I1: Gap_2 | J1: Gap_3 | K1: Gap_4 | L1: HPD_Affordable_2BR_Rent_AMI | M1: CB1_Affordable_Rent_30pct | N1: GAP
A2: 0.3 | B2: =SUM(HNY_CB1_raw1!D2:D8) -> 86 | C2: =VLOOKUP(101, CB_income!$A$2:$B$2, 2, FALSE) -> 198945 | D2: =VLOOKUP(A2,AMI_reference!$A$2:$E$7, 2, FALSE) -> 34020 | E2: =VLOOKUP(A2,AMI_reference!$A$2:$E$7, 3, FALSE) -> 38880 | F2: =VLOOKUP(A2, AMI_reference!$A$2:$E$7, 4, FALSE) -> 43740 | G2: =VLOOKUP(A2,AMI_reference!$A$2:$E$7, 5, FALSE) -> 48600 | H2: =C2-D2 -> 164925 | I2: =C2-E2 -> 160065 | J2: =C2-F2 -> 155205 | K2: =C2-G2 -> 150345 | L2: =VLOOKUP(A2,AMI_rent_2BR!$A$2:$B$13,2,FALSE) -> 1093 | M2: =C2*0.3/12 -> 4973.625 | N2: =M2-L2 -> 3880.625
A3: 0.4 | B3: =SUM(HNY_CB1_raw1!E2:E7) -> 108 | C3: =VLOOKUP(101, CB_income!$A$2:$B$2, 2, FALSE) -> 198945 | D3: =VLOOKUP(A3,AMI_reference!$A$2:$E$7, 2, FALSE) -> 45360 | E3: =VLOOKUP(A3,AMI_reference!$A$2:$E$7, 3, FALSE) -> 51840 | F3: =VLOOKUP(A3, AMI_reference!$A$2:$E$7, 4, FALSE) -> 58320 | G3: =VLOOKUP(A3,AMI_reference!$A$2:$E$7, 5, FALSE) -> 64800 | H3: =C3-D3 -> 153585 | I3: =C3-E3 -> 147105 | J3: =C3-F3 -> 140625 | K3: =C3-G3 -> 134145 | L3: =VLOOKUP(A3,AMI_rent_2BR!$A$2:$B$13,2,FALSE) -> 1458 | M3: =C3*A3/12 -> 6631.5 | N3: =M3-L3 -> 5173.5
A4: 0.6 | B4: =SUM(HNY_CB1_raw1!F2:F8) -> 232 | C4: =VLOOKUP(101, CB_income!$A$2:$B$2, 2, FALSE) -> 198945 | D4: =VLOOKUP(A4,AMI_reference!$A$2:$E$7, 2, FALSE) -> 68040 | E4: =VLOOKUP(A4,AMI_reference!$A$2:$E$7, 3, FALSE) -> 77760 | F4: =VLOOKUP(A4, AMI_reference!$A$2:$E$7, 4, FALSE) -> 87480 | G4: =VLOOKUP(A4,AMI_reference!$A$2:$E$7, 5, FALSE) -> 97200 | H4: =C4-D4 -> 130905 | I4: =C4-E4 -> 121185 | J4: =C4-F4 -> 111465 | K4: =C4-G4 -> 101745 | L4: =VLOOKUP(A4,AMI_rent_2BR!$A$2:$B$13,2,FALSE) -> 2187 | M4: =C4*A4/12 -> 9947.25 | N4: =M4-L4 -> 7760.25
A5: 0.8 | B5: =SUM(HNY_CB1_raw1!G2:G8) -> 298 | C5: =VLOOKUP(101, CB_income!$A$2:$B$2, 2, FALSE) -> 198945 | D5: =VLOOKUP(A5,AMI_reference!$A$2:$E$7, 2, FALSE) -> 90720 | E5: =VLOOKUP(A5,AMI_reference!$A$2:$E$7, 3, FALSE) -> 103680 | F5: =VLOOKUP(A5, AMI_reference!$A$2:$E$7, 4, FALSE) -> 116640 | G5: =VLOOKUP(A5,AMI_reference!$A$2:$E$7, 5, FALSE) -> 129600 | H5: =C5-D5 -> 108225 | I5: =C5-E5 -> 95265 | J5: =C5-F5 -> 82305 | K5: =C5-G5 -> 69345 | L5: =VLOOKUP(A5,AMI_rent_2BR!$A$2:$B$13,2,FALSE) -> 2916 | M5: =C5*A5/12 -> 13263 | N5: =M5-L5 -> 10347
A6: 1.2 | B6: =SUM(HNY_CB1_raw1!H2:H8) -> 48 | C6: =VLOOKUP(101, CB_income!$A$2:$B$2, 2, FALSE) -> 198945 | D6: =VLOOKUP(A6,AMI_reference!$A$2:$E$7, 2, FALSE) -> 136080 | E6: =VLOOKUP(A6,AMI_reference!$A$2:$E$7, 3, FALSE) -> 155520 | F6: =VLOOKUP(A6, AMI_reference!$A$2:$E$7, 4, FALSE) -> 174960 | G6: =VLOOKUP(A6,AMI_reference!$A$2:$E$7, 5, FALSE) -> 194400 | H6: =C6-D6 -> 62865 | I6: =C6-E6 -> 43425 | J6: =C6-F6 -> 23985 | K6: =C6-G6 -> 4545 | L6: =VLOOKUP(A6,AMI_rent_2BR!$A$2:$B$13,2,FALSE) -> 4374 | M6: =C6*A6/12 -> 19894.5 | N6: =M6-L6 -> 15520.5
M12: 2 bedroom is key

Sheet New Data
A1: Affordable Housing Area Media Income (AMI)
A3: ize | B3: 30% AMI | C3: 40% AMI | D3: 50% AMI | E3: 60% AMI | F3: 70% AMI | G3: 80% AMI | H3: 90% AMI | I3: 100% AMI | J3: 110% AMI | K3: 120% AMI | L3: 130% AMI | M3: 165% AMI
A4: Studio | B4: 850 | C4: 1134 | D4: 1417 | E4: 1701 | F4: 1984 | G4: 2268 | H4: 2552 | I4: 2835 | J4: 3119 | K4: 3402 | L4: 3685 | M4: 4678
A5: One-bedroom | B5: 911 | C5: 1215 | D5: 1518 | E5: 1822 | F5: 2126 | G5: 2430 | H5: 2733 | I5: 3037 | J5: 3341 | K5: 3644 | L5: 3948 | M5: 5011
A6: Two-bedroom | B6: 1093 | C6: 1458 | D6: 1822 | E6: 2187 | F6: 2551 | G6: 2916 | H6: 3281 | I6: 3645 | J6: 4010 | K6: 4374 | L6: 4738 | M6: 6014
A13: FAMILY SIZE | B13: 0.3 | C13: 0.4 | D13: 0.5 | E13: 0.6 | F13: 0.7 | G13: 0.8 | H13: 0.9 | I13: 1 | J13: 1.1 | K13: 1.2 | L13: 1.3 | M13: 1.65
A14: 1 | B14: 34020 | C14: 45360 | D14: 56700 | E14: 68040 | F14: 79380 | G14: 90720 | H14: 102060 | I14: 113400 | J14: 124740 | K14: 136080 | L14: 147420 | M14: 187110
A15: 2 | B15: 38880 | C15: 51840 | D15: 64800 | E15: 77760 | F15: 90720 | G15: 103680 | H15: 116640 | I15: 129600 | J15: 142560 | K15: 155520 | L15: 168480 | M15: 213840
A16: 3 | B16: 43740 | C16: 58320 | D16: 72900 | E16: 87480 | F16: 102060 | G16: 116640 | H16: 131220 | I16: 145800 | J16: 160380 | K16: 174960 | L16: 189540 | M16: 240570
A17: 4 | B17: 48600 | C17: 64800 | D17: 81000 | E17: 97200 | F17: 113400 | G17: 129600 | H17: 145800 | I17: 162000 | J17: 178200 | K17: 194400 | L17: 210600 | M17: 267300

Sheet AMI_reference
A1: AMI_Level | B1: Required_Income_1_Person | C1: Required_Income_2_Person | D1: Required_Income_3_Person | E1: Required_Income_4_Person
A2: 0.3 | B2: 34020 | C2: 38880 | D2: 43740 | E2: 48600
A3: 0.4 | B3: 45360 | C3: 51840 | D3: 58320 | E3: 64800
A4: 0.6 | B4: 68040 | C4: 77760 | D4: 87480 | E4: 97200
A5: 0.8 | B5: 90720 | C5: 103680 | D5: 116640 | E5: 129600
A6: 1 | B6: 113400 | C6: 129600 | D6: 145800 | E6: 162000
A7: 1.2 | B7: 136080 | C7: 155520 | D7: 174960 | E7: 194400

Sheet Chart_Data
A1: AMI_Level | B1: HPD_Affordable_2BR_Rent_AMI | C1: CB1_Affordable_Rent_30pct
A2: =Summary!A2 -> 0.3 | B2: =Summary!L2 -> 1093 | C2: =Summary!M2 -> 4973.625
A3: =Summary!A3 -> 0.4 | B3: =Summary!L3 -> 1458 | C3: =Summary!M3 -> 6631.5
A4: =Summary!A4 -> 0.6 | B4: =Summary!L4 -> 2187 | C4: =Summary!M4 -> 9947.25
A5: =Summary!A5 -> 0.8 | B5: =Summary!L5 -> 2916 | C5: =Summary!M5 -> 13263
A6: =Summary!A6 -> 1.2 | B6: =Summary!L6 -> 4374 | C6: =Summary!M6 -> 19894.5

Sheet AMI_rent_2BR
A1: AMI_Level | B1: Max_Rent_2BR
A2: 0.3 | B2: 1093
A3: 0.4 | B3: 1458
A4: 0.5 | B4: 1822
A5: 0.6 | B5: 2187
A6: 0.7 | B6: 2551
A7: 0.8 | B7: 2916
A8: 0.9 | B8: 3281
A9: 1 | B9: 3645
A10: 1.1 | B10: 4010
A11: 1.2 | B11: 4374
A12: 1.3 | B12: 4738
A13: 1.65 | B13: 6014
